odoo/addons/sm_partago_tariffs/__init__.py
odoo/addons/sm_partago_tariffs/__manifest__.py
odoo/addons/sm_partago_tariffs/email_tmpl/abouttoexpire_tariff_email.xml
odoo/addons/sm_partago_tariffs/email_tmpl/notification_tariff_created.xml
odoo/addons/sm_partago_tariffs/models/__init__.py
odoo/addons/sm_partago_tariffs/models/models_sm_company.py
odoo/addons/sm_partago_tariffs/models/models_sm_member.py
odoo/addons/sm_partago_tariffs/models/models_smp_carconfig_price_group.py
odoo/addons/sm_partago_tariffs/models/models_smp_carsharing_send_email_tariff_wizard.py
odoo/addons/sm_partago_tariffs/models/models_smp_carsharing_tariff.py
odoo/addons/sm_partago_tariffs/models/models_smp_carsharing_tariff_history.py
odoo/addons/sm_partago_tariffs/models/models_smp_carsharing_tariff_model.py
odoo/addons/sm_partago_tariffs/models/models_smp_reservation_compute.py
odoo/addons/sm_partago_tariffs/models/models_smp_tariffmodel_price_group.py
odoo/addons/sm_partago_tariffs/models/models_smp_tariffs_cron.py
odoo/addons/sm_partago_tariffs/models/res_config_settings.py
odoo/addons/sm_partago_tariffs/models/smp_car_config.py
odoo/addons/sm_partago_tariffs/security/ir.model.access.csv
odoo/addons/sm_partago_tariffs/views/res_config_settings.xml
odoo/addons/sm_partago_tariffs/views/views.xml
odoo/addons/sm_partago_tariffs/views/views_car_config.xml
odoo/addons/sm_partago_tariffs/views/views_carconfig_price_group.xml
odoo/addons/sm_partago_tariffs/views/views_cron.xml
odoo/addons/sm_partago_tariffs/views/views_members.xml
odoo/addons/sm_partago_tariffs/views/views_reservation_compute.xml
odoo/addons/sm_partago_tariffs/views/views_tariff.xml
odoo/addons/sm_partago_tariffs/views/views_tariff_history.xml
odoo/addons/sm_partago_tariffs/views/views_tariff_model.xml
odoo/addons/sm_partago_tariffs/views/views_tariffmodel_price_group.xml
odoo11_addon_sm_partago_tariffs-11.0.0.0.1.dist-info/METADATA
odoo11_addon_sm_partago_tariffs-11.0.0.0.1.dist-info/WHEEL
odoo11_addon_sm_partago_tariffs-11.0.0.0.1.dist-info/top_level.txt
odoo11_addon_sm_partago_tariffs-11.0.0.0.1.dist-info/RECORD
